{"market": {"ticker": "KXNHL-26-EDM", "result": "no", "close_time": "2026-05-01T05:08:31+00:00", "series_ticker": "KXNHL", "category": "", "volume_fp": 0.0, "last_price_dollars": 0.0, "status": "finalized"}, "candles": [{"end_period_ts": 1772514000, "yes_ask_close": 0.08, "yes_bid_close": 0.06, "volume_fp": 5679.0}, {"end_period_ts": 1772600400, "yes_ask_close": 0.08, "yes_bid_close": 0.06, "volume_fp": 2864.0}, {"end_period_ts": 1772686800, "yes_ask_close": 0.08, "yes_bid_close": 0.07, "volume_fp": 14736.0}, {"end_period_ts": 1772773200, "yes_ask_close": 0.08, "yes_bid_close": 0.07, "volume_fp": 964.0}, {"end_period_ts": 1772859600, "yes_ask_close": 0.07, "yes_bid_close": 0.06, "volume_fp": 4468.0}, {"end_period_ts": 1772946000, "yes_ask_close": 0.07, "yes_bid_close": 0.06, "volume_fp": 5537.0}, {"end_period_ts": 1773032400, "yes_ask_close": 0.07, "yes_bid_close": 0.06, "volume_fp": 2654.0}, {"end_period_ts": 1773115200, "yes_ask_close": 0.07, "yes_bid_close": 0.06, "volume_fp": 10598.0}, {"end_period_ts": 1773201600, "yes_ask_close": 0.08, "yes_bid_close": 0.07, "volume_fp": 1751.0}, {"end_period_ts": 1773288000, "yes_ask_close": 0.08, "yes_bid_close": 0.07, "volume_fp": 2718.0}, {"end_period_ts": 1773374400, "yes_ask_close": 0.08, "yes_bid_close": 0.07, "volume_fp": 3718.0}, {"end_period_ts": 1773460800, "yes_ask_close": 0.07, "yes_bid_close": 0.06, "volume_fp": 1036.0}, {"end_period_ts": 1773547200, "yes_ask_close": 0.07, "yes_bid_close": 0.06, "volume_fp": 1330.0}, {"end_period_ts": 1773633600, "yes_ask_close": 0.07, "yes_bid_close": 0.06, "volume_fp": 2121.0}, {"end_period_ts": 1773720000, "yes_ask_close": 0.07, "yes_bid_close": 0.06, "volume_fp": 1884.0}, {"end_period_ts": 1773806400, "yes_ask_close": 0.07, "yes_bid_close": 0.05, "volume_fp": 15659.0}, {"end_period_ts": 1773892800, "yes_ask_close": 0.05, "yes_bid_close": 0.04, "volume_fp": 26275.0}, {"end_period_ts": 1773979200, "yes_ask_close": 0.06, "yes_bid_close": 0.04, "volume_fp": 11311.0}, {"end_period_ts": 1774065600, "yes_ask_close": 0.06, "yes_bid_close": 0.04, "volume_fp": 388.0}, {"end_period_ts": 1774152000, "yes_ask_close": 0.06, "yes_bid_close": 0.05, "volume_fp": 11169.0}, {"end_period_ts": 1774238400, "yes_ask_close": 0.05, "yes_bid_close": 0.04, "volume_fp": 1548.0}, {"end_period_ts": 1774324800, "yes_ask_close": 0.05, "yes_bid_close": 0.04, "volume_fp": 9407.0}, {"end_period_ts": 1774411200, "yes_ask_close": 0.05, "yes_bid_close": 0.04, "volume_fp": 10182.0}, {"end_period_ts": 1774497600, "yes_ask_close": 0.05, "yes_bid_close": 0.04, "volume_fp": 759.0}, {"end_period_ts": 1774584000, "yes_ask_close": 0.06, "yes_bid_close": 0.05, "volume_fp": 11442.0}, {"end_period_ts": 1774670400, "yes_ask_close": 0.06, "yes_bid_close": 0.05, "volume_fp": 4194.0}, {"end_period_ts": 1774756800, "yes_ask_close": 0.06, "yes_bid_close": 0.05, "volume_fp": 1516.0}, {"end_period_ts": 1774843200, "yes_ask_close": 0.06, "yes_bid_close": 0.05, "volume_fp": 11977.0}, {"end_period_ts": 1774929600, "yes_ask_close": 0.06, "yes_bid_close": 0.05, "volume_fp": 8947.0}, {"end_period_ts": 1775016000, "yes_ask_close": 0.07, "yes_bid_close": 0.06, "volume_fp": 43632.0}, {"end_period_ts": 1775102400, "yes_ask_close": 0.08, "yes_bid_close": 0.07, "volume_fp": 21632.0}, {"end_period_ts": 1775188800, "yes_ask_close": 0.09, "yes_bid_close": 0.08, "volume_fp": 59404.0}, {"end_period_ts": 1775275200, "yes_ask_close": 0.09, "yes_bid_close": 0.08, "volume_fp": 6280.0}, {"end_period_ts": 1775361600, "yes_ask_close": 0.09, "yes_bid_close": 0.08, "volume_fp": 40009.0}, {"end_period_ts": 1775448000, "yes_ask_close": 0.09, "yes_bid_close": 0.08, "volume_fp": 7632.0}, {"end_period_ts": 1775534400, "yes_ask_close": 0.09, "yes_bid_close": 0.08, "volume_fp": 16478.0}, {"end_period_ts": 1775620800, "yes_ask_close": 0.09, "yes_bid_close": 0.08, "volume_fp": 36237.0}, {"end_period_ts": 1775707200, "yes_ask_close": 0.09, "yes_bid_close": 0.08, "volume_fp": 14860.0}, {"end_period_ts": 1775793600, "yes_ask_close": 0.09, "yes_bid_close": 0.08, "volume_fp": 4139.0}, {"end_period_ts": 1775880000, "yes_ask_close": 0.09, "yes_bid_close": 0.08, "volume_fp": 11574.0}, {"end_period_ts": 1775966400, "yes_ask_close": 0.08, "yes_bid_close": 0.07, "volume_fp": 14833.0}, {"end_period_ts": 1776052800, "yes_ask_close": 0.08, "yes_bid_close": 0.07, "volume_fp": 55361.0}, {"end_period_ts": 1776139200, "yes_ask_close": 0.07, "yes_bid_close": 0.06, "volume_fp": 98828.0}, {"end_period_ts": 1776225600, "yes_ask_close": 0.07, "yes_bid_close": 0.06, "volume_fp": 11543.0}, {"end_period_ts": 1776312000, "yes_ask_close": 0.07, "yes_bid_close": 0.06, "volume_fp": 19013.0}, {"end_period_ts": 1776398400, "yes_ask_close": 0.08, "yes_bid_close": 0.07, "volume_fp": 54698.41}, {"end_period_ts": 1776484800, "yes_ask_close": 0.09, "yes_bid_close": 0.07, "volume_fp": 79432.54}, {"end_period_ts": 1776571200, "yes_ask_close": 0.08, "yes_bid_close": 0.07, "volume_fp": 89610.38}, {"end_period_ts": 1776657600, "yes_ask_close": 0.08, "yes_bid_close": 0.06, "volume_fp": 67700.13}, {"end_period_ts": 1776744000, "yes_ask_close": 0.09, "yes_bid_close": 0.08, "volume_fp": 208313.37}, {"end_period_ts": 1776830400, "yes_ask_close": 0.09, "yes_bid_close": 0.08, "volume_fp": 75347.59}, {"end_period_ts": 1776916800, "yes_ask_close": 0.09, "yes_bid_close": 0.08, "volume_fp": 171441.98}, {"end_period_ts": 1777003200, "yes_ask_close": 0.08, "yes_bid_close": 0.06, "volume_fp": 31258.27}, {"end_period_ts": 1777089600, "yes_ask_close": 0.08, "yes_bid_close": 0.07, "volume_fp": 21125.5}, {"end_period_ts": 1777176000, "yes_ask_close": 0.06, "yes_bid_close": 0.04, "volume_fp": 45767.92}, {"end_period_ts": 1777262400, "yes_ask_close": 0.07, "yes_bid_close": 0.06, "volume_fp": 84443.56}, {"end_period_ts": 1777348800, "yes_ask_close": 0.03, "yes_bid_close": 0.02, "volume_fp": 65390.76}, {"end_period_ts": 1777435200, "yes_ask_close": 0.04, "yes_bid_close": 0.03, "volume_fp": 54514.67}, {"end_period_ts": 1777521600, "yes_ask_close": 0.04, "yes_bid_close": 0.03, "volume_fp": 30786.53}, {"end_period_ts": 1777608000, "yes_ask_close": 0.01, "yes_bid_close": 0.0, "volume_fp": 61084.5}], "close_ts": 1777612111}