{"market": {"ticker": "KXCPIYOY-26APR-T3.9", "result": "no", "close_time": "2026-05-12T12:29:00+00:00", "series_ticker": "KXCPIYOY", "category": "", "volume_fp": 0.0, "last_price_dollars": 0.0, "status": "finalized"}, "candles": [{"end_period_ts": 1773633600, "yes_ask_close": 0.99, "yes_bid_close": 0.01, "volume_fp": 0.0}, {"end_period_ts": 1773720000, "yes_ask_close": 0.06, "yes_bid_close": 0.01, "volume_fp": 2.0}, {"end_period_ts": 1773806400, "yes_ask_close": 0.89, "yes_bid_close": 0.02, "volume_fp": 47.0}, {"end_period_ts": 1773892800, "yes_ask_close": 0.9, "yes_bid_close": 0.01, "volume_fp": 0.0}, {"end_period_ts": 1773979200, "yes_ask_close": 0.9, "yes_bid_close": 0.01, "volume_fp": 0.0}, {"end_period_ts": 1774065600, "yes_ask_close": 0.9, "yes_bid_close": 0.01, "volume_fp": 0.0}, {"end_period_ts": 1774324800, "yes_ask_close": 0.9, "yes_bid_close": 0.01, "volume_fp": 0.0}, {"end_period_ts": 1774411200, "yes_ask_close": 0.9, "yes_bid_close": 0.01, "volume_fp": 0.0}, {"end_period_ts": 1774497600, "yes_ask_close": 0.5, "yes_bid_close": 0.01, "volume_fp": 0.0}, {"end_period_ts": 1774584000, "yes_ask_close": 0.85, "yes_bid_close": 0.01, "volume_fp": 0.0}, {"end_period_ts": 1774670400, "yes_ask_close": 0.85, "yes_bid_close": 0.01, "volume_fp": 10.0}, {"end_period_ts": 1774756800, "yes_ask_close": 0.85, "yes_bid_close": 0.01, "volume_fp": 0.0}, {"end_period_ts": 1774843200, "yes_ask_close": 0.85, "yes_bid_close": 0.02, "volume_fp": 3.0}, {"end_period_ts": 1774929600, "yes_ask_close": 0.16, "yes_bid_close": 0.05, "volume_fp": 0.0}, {"end_period_ts": 1775016000, "yes_ask_close": 0.17, "yes_bid_close": 0.06, "volume_fp": 0.0}, {"end_period_ts": 1775102400, "yes_ask_close": 0.19, "yes_bid_close": 0.08, "volume_fp": 0.0}, {"end_period_ts": 1775188800, "yes_ask_close": 0.22, "yes_bid_close": 0.11, "volume_fp": 0.0}, {"end_period_ts": 1775275200, "yes_ask_close": 0.28, "yes_bid_close": 0.17, "volume_fp": 0.0}, {"end_period_ts": 1775361600, "yes_ask_close": 0.27, "yes_bid_close": 0.18, "volume_fp": 3.0}, {"end_period_ts": 1775448000, "yes_ask_close": 0.27, "yes_bid_close": 0.16, "volume_fp": 0.0}, {"end_period_ts": 1775534400, "yes_ask_close": 0.34, "yes_bid_close": 0.23, "volume_fp": 9.0}, {"end_period_ts": 1775620800, "yes_ask_close": 0.75, "yes_bid_close": 0.04, "volume_fp": 716.0}, {"end_period_ts": 1775707200, "yes_ask_close": 0.18, "yes_bid_close": 0.1, "volume_fp": 118.0}, {"end_period_ts": 1775793600, "yes_ask_close": 0.17, "yes_bid_close": 0.06, "volume_fp": 0.0}, {"end_period_ts": 1775880000, "yes_ask_close": 0.47, "yes_bid_close": 0.02, "volume_fp": 0.0}, {"end_period_ts": 1775966400, "yes_ask_close": 0.15, "yes_bid_close": 0.08, "volume_fp": 163.0}, {"end_period_ts": 1776052800, "yes_ask_close": 0.26, "yes_bid_close": 0.19, "volume_fp": 247.0}, {"end_period_ts": 1776139200, "yes_ask_close": 0.09, "yes_bid_close": 0.06, "volume_fp": 1181.31}, {"end_period_ts": 1776225600, "yes_ask_close": 0.07, "yes_bid_close": 0.04, "volume_fp": 1202.5}, {"end_period_ts": 1776312000, "yes_ask_close": 0.07, "yes_bid_close": 0.03, "volume_fp": 1.0}, {"end_period_ts": 1776398400, "yes_ask_close": 0.08, "yes_bid_close": 0.05, "volume_fp": 965.86}, {"end_period_ts": 1776484800, "yes_ask_close": 0.04, "yes_bid_close": 0.01, "volume_fp": 2.0}, {"end_period_ts": 1776571200, "yes_ask_close": 0.04, "yes_bid_close": 0.02, "volume_fp": 134.0}, {"end_period_ts": 1776657600, "yes_ask_close": 0.04, "yes_bid_close": 0.03, "volume_fp": 805.74}, {"end_period_ts": 1776744000, "yes_ask_close": 0.04, "yes_bid_close": 0.03, "volume_fp": 904.0}, {"end_period_ts": 1776830400, "yes_ask_close": 0.03, "yes_bid_close": 0.01, "volume_fp": 1983.31}, {"end_period_ts": 1776916800, "yes_ask_close": 0.03, "yes_bid_close": 0.01, "volume_fp": 31.0}, {"end_period_ts": 1777003200, "yes_ask_close": 0.04, "yes_bid_close": 0.03, "volume_fp": 7824.76}, {"end_period_ts": 1777089600, "yes_ask_close": 0.04, "yes_bid_close": 0.03, "volume_fp": 2279.0}, {"end_period_ts": 1777176000, "yes_ask_close": 0.04, "yes_bid_close": 0.03, "volume_fp": 0.0}, {"end_period_ts": 1777262400, "yes_ask_close": 0.04, "yes_bid_close": 0.03, "volume_fp": 12.0}, {"end_period_ts": 1777348800, "yes_ask_close": 0.04, "yes_bid_close": 0.03, "volume_fp": 119.0}, {"end_period_ts": 1777435200, "yes_ask_close": 0.03, "yes_bid_close": 0.02, "volume_fp": 2719.0}, {"end_period_ts": 1777521600, "yes_ask_close": 0.04, "yes_bid_close": 0.03, "volume_fp": 3100.09}, {"end_period_ts": 1777608000, "yes_ask_close": 0.03, "yes_bid_close": 0.02, "volume_fp": 7442.0}, {"end_period_ts": 1777694400, "yes_ask_close": 0.03, "yes_bid_close": 0.02, "volume_fp": 11446.8}, {"end_period_ts": 1777780800, "yes_ask_close": 0.04, "yes_bid_close": 0.03, "volume_fp": 503.85}, {"end_period_ts": 1777867200, "yes_ask_close": 0.03, "yes_bid_close": 0.0, "volume_fp": 4837.5}, {"end_period_ts": 1777953600, "yes_ask_close": 0.03, "yes_bid_close": 0.02, "volume_fp": 16419.39}, {"end_period_ts": 1778040000, "yes_ask_close": 0.03, "yes_bid_close": 0.02, "volume_fp": 4451.0}, {"end_period_ts": 1778126400, "yes_ask_close": 0.04, "yes_bid_close": 0.02, "volume_fp": 4229.08}, {"end_period_ts": 1778212800, "yes_ask_close": 0.03, "yes_bid_close": 0.02, "volume_fp": 7368.95}, {"end_period_ts": 1778299200, "yes_ask_close": 0.03, "yes_bid_close": 0.01, "volume_fp": 12072.0}, {"end_period_ts": 1778385600, "yes_ask_close": 0.03, "yes_bid_close": 0.01, "volume_fp": 2517.92}, {"end_period_ts": 1778472000, "yes_ask_close": 0.03, "yes_bid_close": 0.01, "volume_fp": 4348.04}, {"end_period_ts": 1778558400, "yes_ask_close": 0.03, "yes_bid_close": 0.02, "volume_fp": 18204.46}], "close_ts": 1778588940}